geo_retriever/__init__.py
geo_retriever/definitions.py
geo_retriever/geo_retriever.py
geo_retriever/retriever.py
geo_retriever/heatflow/__init__.py
geo_retriever/heatflow/get_heatflow.py
geo_retriever/surface_temperature/__init__.py
geo_retriever/uk_seismic/__init__.py
georetriever/__init__.py
georetriever/data.py
georetriever/geo_cutout.py
georetriever/gis.py
georetriever/datasets/__init__.py
georetriever/datasets/era5.py
georetriever/datasets/macrostrat.py
georetriever/plotting/__init__.py
georetriever/plotting/plot_lith.py
georetriever/utils/__init__.py
georetriever/utils/geo_utils.py
test/__init__.py
test/test_geocutout.py
test/test_lith.py
georetriever-0.1.1.dist-info/AUTHORS.rst
georetriever-0.1.1.dist-info/LICENSE
georetriever-0.1.1.dist-info/METADATA
georetriever-0.1.1.dist-info/WHEEL
georetriever-0.1.1.dist-info/top_level.txt
georetriever-0.1.1.dist-info/RECORD
