Metadata-Version: 2.1
Name: georetriever
Version: 0.1.1
Summary: Retrieve geological data for geothermal systems from coordinates in Python!
Home-page: UNKNOWN
Author: Lukas Franken, Hui Ben, Heather Kennedy, Nikolaos Reppas
Author-email: <lukas.franken@ed.ac.uk>
License: UNKNOWN
Keywords: python,geo,geological,heatflow,thermal,lithography,conductivity
Platform: UNKNOWN
Classifier: Development Status :: 1 - Planning
Classifier: Intended Audience :: Developers
Classifier: Programming Language :: Python :: 3
Classifier: Operating System :: Unix
Classifier: Operating System :: MacOS :: MacOS X
Classifier: Operating System :: Microsoft :: Windows
License-File: LICENSE
License-File: AUTHORS.rst
Requires-Dist: numpy
Requires-Dist: scipy
Requires-Dist: pandas (>=0.25)
Requires-Dist: bottleneck
Requires-Dist: numexpr
Requires-Dist: xarray (>=0.20)
Requires-Dist: netcdf4
Requires-Dist: dask (>=2021.10.0)
Requires-Dist: toolz
Requires-Dist: requests
Requires-Dist: pyyaml
Requires-Dist: rasterio (>1.2.10)
Requires-Dist: shapely
Requires-Dist: progressbar2
Requires-Dist: tqdm
Requires-Dist: pyproj (>=2)
Requires-Dist: geopandas
Requires-Dist: cdsapi
Requires-Dist: Pillow
Provides-Extra: dev
Requires-Dist: pre-commit ; extra == 'dev'
Requires-Dist: pytest ; extra == 'dev'
Requires-Dist: pytest-cov ; extra == 'dev'
